Workbook

Sheet Dashboard
B2: AUTOMATED SARI-SARI STORE MANAGEMENT SYSTEM
B3: Live Dashboard
B5: TODAY'S SALES | D5: TODAY'S PROFIT | F5: MONTH SALES
B6: =SUMIFS('Sales Log'!$H$4:$H$120,'Sales Log'!$A$4:$A$120,TODAY()) -> 301 | D6: =SUMIFS('Sales Log'!$J$4:$J$120,'Sales Log'!$A$4:$A$120,TODAY()) -> 85 | F6: =SUMIFS('Sales Log'!$H$4:$H$120,'Sales Log'!$A$4:$A$120,">="&DATE(YEAR(TODAY()),MONTH(TODAY()),1),'Sales Log'!$A$4:$A$120,"<="&EOMONTH(TODAY(),0)) -> 301
B8: RESTOCK ALERTS | D8: UTANG / CREDIT | F8: STOCK VALUE
B9: =COUNTIF(Inventory!$H$4:$H$21,"REORDER") -> 3 | D9: =SUMIF('Credit Ledger'!$G$4:$G$60,">0") -> 6 | F9: =SUM(Inventory!$I$4:$I$21) -> 13849
B11: LIVE STOCK DASHBOARD
B12: Product Name | C12: Current Stock | D12: Reorder Level | E12: Status
B13: =Inventory!B4 -> Coke Mismo 300ml | C13: =Inventory!F4 -> 46 | D13: =Inventory!G4 -> 15 | E13: =IF(Inventory!H4="REORDER","REORDER NOW","OK") -> OK
B14: =Inventory!B5 -> Royal Tru-Orange 300ml | C14: =Inventory!F5 -> 30 | D14: =Inventory!G5 -> 15 | E14: =IF(Inventory!H5="REORDER","REORDER NOW","OK") -> OK
B15: =Inventory!B6 -> Sprite 300ml | C15: =Inventory!F6 -> 12 | D15: =Inventory!G6 -> 15 | E15: =IF(Inventory!H6="REORDER","REORDER NOW","OK") -> REORDER NOW
B16: =Inventory!B7 -> Lucky Me Pancit Canton | C16: =Inventory!F7 -> 120 | D16: =Inventory!G7 -> 30 | E16: =IF(Inventory!H7="REORDER","REORDER NOW","OK") -> OK
B17: =Inventory!B8 -> Lucky Me Instant Mami | C17: =Inventory!F8 -> 78 | D17: =Inventory!G8 -> 30 | E17: =IF(Inventory!H8="REORDER","REORDER NOW","OK") -> OK
B18: =Inventory!B9 -> Nescafe 3in1 Coffee | C18: =Inventory!F9 -> 10 | D18: =Inventory!G9 -> 20 | E18: =IF(Inventory!H9="REORDER","REORDER NOW","OK") -> REORDER NOW
B19: =Inventory!B10 -> Great Taste White Coffee | C19: =Inventory!F10 -> 55 | D19: =Inventory!G10 -> 20 | E19: =IF(Inventory!H10="REORDER","REORDER NOW","OK") -> OK
B20: =Inventory!B11 -> Bear Brand Powder 33g | C20: =Inventory!F11 -> 40 | D20: =Inventory!G11 -> 15 | E20: =IF(Inventory!H11="REORDER","REORDER NOW","OK") -> OK
B21: =Inventory!B12 -> Alaska Powder 33g | C21: =Inventory!F12 -> 8 | D21: =Inventory!G12 -> 15 | E21: =IF(Inventory!H12="REORDER","REORDER NOW","OK") -> REORDER NOW
B22: =Inventory!B13 -> Argentinian Hotdog 250g | C22: =Inventory!F13 -> 20 | D22: =Inventory!G13 -> 8 | E22: =IF(Inventory!H13="REORDER","REORDER NOW","OK") -> OK
B23: =Inventory!B14 -> CDO Karne Norte 100g | C23: =Inventory!F14 -> 25 | D23: =Inventory!G14 -> 10 | E23: =IF(Inventory!H14="REORDER","REORDER NOW","OK") -> OK
B24: =Inventory!B15 -> Lucky Me! Go Cup | C24: =Inventory!F15 -> 30 | D24: =Inventory!G15 -> 10 | E24: =IF(Inventory!H15="REORDER","REORDER NOW","OK") -> OK
... B30: =Inventory!B21 -> Silver Swan Soy Sauce 350ml | C30: =Inventory!F21 -> 22 | D30: =Inventory!G21 -> 8 | E30: =IF(Inventory!H21="REORDER","REORDER NOW","OK") -> OK
B32: DAILY SALES & PROFIT (LAST 7 DAYS)
B51: TOP SELLING PRODUCTS (BY QUANTITY)

Sheet Sales Log
A1: DAILY SALES TRANSACTION LOG
A3: Date | B3: Time | C3: Trans No | D3: Product ID | E3: Product Name | F3: Qty | G3: Unit Price (₱) | H3: Total Sale (₱) | I3: Cost (₱) | J3: Profit (₱) | K3: Payment | L3: Customer Name
A4: =IF(D4="","",IF(N(A4)=0,TODAY(),A4)) -> 46302 | B4: =IF(D4="","",IF(N(B4)=0,ROUND(MOD(NOW(),1)*1440,0)/1440,B4)) -> 0.19722222 | C4: =IF(D4="","","T"&(1000+COUNTIF($D$4:D4,"<>"))) -> T1001 | D4: P001 | E4: =IF(D4="","",VLOOKUP(D4,Inventory!$A$4:$I$21,2,FALSE())) -> Coke Mismo 300ml | F4: 5 | G4: =IF(D4="","",VLOOKUP(D4,Inventory!$A$4:$I$21,5,FALSE())) -> 25 | H4: =IF(OR(D4="",F4=""),"",F4*G4) -> 125 | I4: =IF(OR(D4="",F4=""),"",F4*VLOOKUP(D4,Inventory!$A$4:$I$21,4,FALSE())) -> 90 | J4: =IF(H4="","",H4-I4) -> 35 | K4: Cash | Z4: =IF(K4="Credit",COUNTIF(K$4:K4,"Credit"),"")
A5: =IF(D5="","",IF(N(A5)=0,TODAY(),A5)) -> 46302 | B5: =IF(D5="","",IF(N(B5)=0,ROUND(MOD(NOW(),1)*1440,0)/1440,B5)) -> 0.19722222 | C5: =IF(D5="","","T"&(1000+COUNTIF($D$4:D5,"<>"))) -> T1002 | D5: P002 | E5: =IF(D5="","",VLOOKUP(D5,Inventory!$A$4:$I$21,2,FALSE())) -> Royal Tru-Orange 300ml | F5: 6 | G5: =IF(D5="","",VLOOKUP(D5,Inventory!$A$4:$I$21,5,FALSE())) -> 25 | H5: =IF(OR(D5="",F5=""),"",F5*G5) -> 150 | I5: =IF(OR(D5="",F5=""),"",F5*VLOOKUP(D5,Inventory!$A$4:$I$21,4,FALSE())) -> 108 | J5: =IF(H5="","",H5-I5) -> 42 | K5: Cash | Z5: =IF(K5="Credit",COUNTIF(K$4:K5,"Credit"),"")
A6: =IF(D6="","",IF(N(A6)=0,TODAY(),A6)) -> 46302 | B6: =IF(D6="","",IF(N(B6)=0,ROUND(MOD(NOW(),1)*1440,0)/1440,B6)) -> 0.19722222 | C6: =IF(D6="","","T"&(1000+COUNTIF($D$4:D6,"<>"))) -> T1003 | D6: P005 | E6: =IF(D6="","",VLOOKUP(D6,Inventory!$A$4:$I$21,2,FALSE())) -> Lucky Me Instant Mami | F6: 2 | G6: =IF(D6="","",VLOOKUP(D6,Inventory!$A$4:$I$21,5,FALSE())) -> 13 | H6: =IF(OR(D6="",F6=""),"",F6*G6) -> 26 | I6: =IF(OR(D6="",F6=""),"",F6*VLOOKUP(D6,Inventory!$A$4:$I$21,4,FALSE())) -> 18 | J6: =IF(H6="","",H6-I6) -> 8 | K6: Credit | L6: Magtalas | Z6: =IF(K6="Credit",COUNTIF(K$4:K6,"Credit"),"") -> 1
A7: =IF(D7="","",IF(N(A7)=0,TODAY(),A7)) | B7: =IF(D7="","",IF(N(B7)=0,ROUND(MOD(NOW(),1)*1440,0)/1440,B7)) | C7: =IF(D7="","","T"&(1000+COUNTIF($D$4:D7,"<>"))) | E7: =IF(D7="","",VLOOKUP(D7,Inventory!$A$4:$I$21,2,FALSE())) | G7: =IF(D7="","",VLOOKUP(D7,Inventory!$A$4:$I$21,5,FALSE())) | H7: =IF(OR(D7="",F7=""),"",F7*G7) | I7: =IF(OR(D7="",F7=""),"",F7*VLOOKUP(D7,Inventory!$A$4:$I$21,4,FALSE())) | J7: =IF(H7="","",H7-I7) | Z7: =IF(K7="Credit",COUNTIF(K$4:K7,"Credit"),"")
A8: =IF(D8="","",IF(N(A8)=0,TODAY(),A8)) | B8: =IF(D8="","",IF(N(B8)=0,ROUND(MOD(NOW(),1)*1440,0)/1440,B8)) | C8: =IF(D8="","","T"&(1000+COUNTIF($D$4:D8,"<>"))) | E8: =IF(D8="","",VLOOKUP(D8,Inventory!$A$4:$I$21,2,FALSE())) | G8: =IF(D8="","",VLOOKUP(D8,Inventory!$A$4:$I$21,5,FALSE())) | H8: =IF(OR(D8="",F8=""),"",F8*G8) | I8: =IF(OR(D8="",F8=""),"",F8*VLOOKUP(D8,Inventory!$A$4:$I$21,4,FALSE())) | J8: =IF(H8="","",H8-I8) | Z8: =IF(K8="Credit",COUNTIF(K$4:K8,"Credit"),"")
A9: =IF(D9="","",IF(N(A9)=0,TODAY(),A9)) | B9: =IF(D9="","",IF(N(B9)=0,ROUND(MOD(NOW(),1)*1440,0)/1440,B9)) | C9: =IF(D9="","","T"&(1000+COUNTIF($D$4:D9,"<>"))) | E9: =IF(D9="","",VLOOKUP(D9,Inventory!$A$4:$I$21,2,FALSE())) | G9: =IF(D9="","",VLOOKUP(D9,Inventory!$A$4:$I$21,5,FALSE())) | H9: =IF(OR(D9="",F9=""),"",F9*G9) | I9: =IF(OR(D9="",F9=""),"",F9*VLOOKUP(D9,Inventory!$A$4:$I$21,4,FALSE())) | J9: =IF(H9="","",H9-I9) | Z9: =IF(K9="Credit",COUNTIF(K$4:K9,"Credit"),"")
A10: =IF(D10="","",IF(N(A10)=0,TODAY(),A10)) | B10: =IF(D10="","",IF(N(B10)=0,ROUND(MOD(NOW(),1)*1440,0)/1440,B10)) | C10: =IF(D10="","","T"&(1000+COUNTIF($D$4:D10,"<>"))) | E10: =IF(D10="","",VLOOKUP(D10,Inventory!$A$4:$I$21,2,FALSE())) | G10: =IF(D10="","",VLOOKUP(D10,Inventory!$A$4:$I$21,5,FALSE())) | H10: =IF(OR(D10="",F10=""),"",F10*G10) | I10: =IF(OR(D10="",F10=""),"",F10*VLOOKUP(D10,Inventory!$A$4:$I$21,4,FALSE())) | J10: =IF(H10="","",H10-I10) | Z10: =IF(K10="Credit",COUNTIF(K$4:K10,"Credit"),"")
A11: =IF(D11="","",IF(N(A11)=0,TODAY(),A11)) | B11: =IF(D11="","",IF(N(B11)=0,ROUND(MOD(NOW(),1)*1440,0)/1440,B11)) | C11: =IF(D11="","","T"&(1000+COUNTIF($D$4:D11,"<>"))) | E11: =IF(D11="","",VLOOKUP(D11,Inventory!$A$4:$I$21,2,FALSE())) | G11: =IF(D11="","",VLOOKUP(D11,Inventory!$A$4:$I$21,5,FALSE())) | H11: =IF(OR(D11="",F11=""),"",F11*G11) | I11: =IF(OR(D11="",F11=""),"",F11*VLOOKUP(D11,Inventory!$A$4:$I$21,4,FALSE())) | J11: =IF(H11="","",H11-I11) | Z11: =IF(K11="Credit",COUNTIF(K$4:K11,"Credit"),"")
A12: =IF(D12="","",IF(N(A12)=0,TODAY(),A12)) | B12: =IF(D12="","",IF(N(B12)=0,ROUND(MOD(NOW(),1)*1440,0)/1440,B12)) | C12: =IF(D12="","","T"&(1000+COUNTIF($D$4:D12,"<>"))) | E12: =IF(D12="","",VLOOKUP(D12,Inventory!$A$4:$I$21,2,FALSE())) | G12: =IF(D12="","",VLOOKUP(D12,Inventory!$A$4:$I$21,5,FALSE())) | H12: =IF(OR(D12="",F12=""),"",F12*G12) | I12: =IF(OR(D12="",F12=""),"",F12*VLOOKUP(D12,Inventory!$A$4:$I$21,4,FALSE())) | J12: =IF(H12="","",H12-I12) | Z12: =IF(K12="Credit",COUNTIF(K$4:K12,"Credit"),"")
A13: =IF(D13="","",IF(N(A13)=0,TODAY(),A13)) | B13: =IF(D13="","",IF(N(B13)=0,ROUND(MOD(NOW(),1)*1440,0)/1440,B13)) | C13: =IF(D13="","","T"&(1000+COUNTIF($D$4:D13,"<>"))) | E13: =IF(D13="","",VLOOKUP(D13,Inventory!$A$4:$I$21,2,FALSE())) | G13: =IF(D13="","",VLOOKUP(D13,Inventory!$A$4:$I$21,5,FALSE())) | H13: =IF(OR(D13="",F13=""),"",F13*G13) | I13: =IF(OR(D13="",F13=""),"",F13*VLOOKUP(D13,Inventory!$A$4:$I$21,4,FALSE())) | J13: =IF(H13="","",H13-I13) | Z13: =IF(K13="Credit",COUNTIF(K$4:K13,"Credit"),"")
A14: =IF(D14="","",IF(N(A14)=0,TODAY(),A14)) | B14: =IF(D14="","",IF(N(B14)=0,ROUND(MOD(NOW(),1)*1440,0)/1440,B14)) | C14: =IF(D14="","","T"&(1000+COUNTIF($D$4:D14,"<>"))) | E14: =IF(D14="","",VLOOKUP(D14,Inventory!$A$4:$I$21,2,FALSE())) | G14: =IF(D14="","",VLOOKUP(D14,Inventory!$A$4:$I$21,5,FALSE())) | H14: =IF(OR(D14="",F14=""),"",F14*G14) | I14: =IF(OR(D14="",F14=""),"",F14*VLOOKUP(D14,Inventory!$A$4:$I$21,4,FALSE())) | J14: =IF(H14="","",H14-I14) | Z14: =IF(K14="Credit",COUNTIF(K$4:K14,"Credit"),"")
A15: =IF(D15="","",IF(N(A15)=0,TODAY(),A15)) | B15: =IF(D15="","",IF(N(B15)=0,ROUND(MOD(NOW(),1)*1440,0)/1440,B15)) | C15: =IF(D15="","","T"&(1000+COUNTIF($D$4:D15,"<>"))) | E15: =IF(D15="","",VLOOKUP(D15,Inventory!$A$4:$I$21,2,FALSE())) | G15: =IF(D15="","",VLOOKUP(D15,Inventory!$A$4:$I$21,5,FALSE())) | H15: =IF(OR(D15="",F15=""),"",F15*G15) | I15: =IF(OR(D15="",F15=""),"",F15*VLOOKUP(D15,Inventory!$A$4:$I$21,4,FALSE())) | J15: =IF(H15="","",H15-I15) | Z15: =IF(K15="Credit",COUNTIF(K$4:K15,"Credit"),"")
A16: =IF(D16="","",IF(N(A16)=0,TODAY(),A16)) | B16: =IF(D16="","",IF(N(B16)=0,ROUND(MOD(NOW(),1)*1440,0)/1440,B16)) | C16: =IF(D16="","","T"&(1000+COUNTIF($D$4:D16,"<>"))) | E16: =IF(D16="","",VLOOKUP(D16,Inventory!$A$4:$I$21,2,FALSE())) | G16: =IF(D16="","",VLOOKUP(D16,Inventory!$A$4:$I$21,5,FALSE())) | H16: =IF(OR(D16="",F16=""),"",F16*G16) | I16: =IF(OR(D16="",F16=""),"",F16*VLOOKUP(D16,Inventory!$A$4:$I$21,4,FALSE())) | J16: =IF(H16="","",H16-I16) | Z16: =IF(K16="Credit",COUNTIF(K$4:K16,"Credit"),"")
A17: =IF(D17="","",IF(N(A17)=0,TODAY(),A17)) | B17: =IF(D17="","",IF(N(B17)=0,ROUND(MOD(NOW(),1)*1440,0)/1440,B17)) | C17: =IF(D17="","","T"&(1000+COUNTIF($D$4:D17,"<>"))) | E17: =IF(D17="","",VLOOKUP(D17,Inventory!$A$4:$I$21,2,FALSE())) | G17: =IF(D17="","",VLOOKUP(D17,Inventory!$A$4:$I$21,5,FALSE())) | H17: =IF(OR(D17="",F17=""),"",F17*G17) | I17: =IF(OR(D17="",F17=""),"",F17*VLOOKUP(D17,Inventory!$A$4:$I$21,4,FALSE())) | J17: =IF(H17="","",H17-I17) | Z17: =IF(K17="Credit",COUNTIF(K$4:K17,"Credit"),"")
A18: =IF(D18="","",IF(N(A18)=0,TODAY(),A18)) | B18: =IF(D18="","",IF(N(B18)=0,ROUND(MOD(NOW(),1)*1440,0)/1440,B18)) | C18: =IF(D18="","","T"&(1000+COUNTIF($D$4:D18,"<>"))) | E18: =IF(D18="","",VLOOKUP(D18,Inventory!$A$4:$I$21,2,FALSE())) | G18: =IF(D18="","",VLOOKUP(D18,Inventory!$A$4:$I$21,5,FALSE())) | H18: =IF(OR(D18="",F18=""),"",F18*G18) | I18: =IF(OR(D18="",F18=""),"",F18*VLOOKUP(D18,Inventory!$A$4:$I$21,4,FALSE())) | J18: =IF(H18="","",H18-I18) | Z18: =IF(K18="Credit",COUNTIF(K$4:K18,"Credit"),"")
... A120: =IF(D120="","",IF(N(A120)=0,TODAY(),A120)) | B120: =IF(D120="","",IF(N(B120)=0,ROUND(MOD(NOW(),1)*1440,0)/1440,B120)) | C120: =IF(D120="","","T"&(1000+COUNTIF($D$4:D120,"<>"))) | E120: =IF(D120="","",VLOOKUP(D120,Inventory!$A$4:$I$21,2,FALSE())) | G120: =IF(D120="","",VLOOKUP(D120,Inventory!$A$4:$I$21,5,FALSE())) | H120: =IF(OR(D120="",F120=""),"",F120*G120) | I120: =IF(OR(D120="",F120=""),"",F120*VLOOKUP(D120,Inventory!$A$4:$I$21,4,FALSE())) | J120: =IF(H120="","",H120-I120) | Z120: =IF(K120="Credit",COUNTIF(K$4:K120,"Credit"),"")

Sheet Inventory
A1: PRODUCT MASTER LIST & INVENTORY
A3: Product ID | B3: Product Name | C3: Category | D3: Cost Price (₱) | E3: Selling Price (₱) | F3: Current Stock | G3: Reorder Level | H3: Status | I3: Stock Value (₱) | K3: Opening Stock
A4: P001 | B4: Coke Mismo 300ml | C4: Drinks | D4: 18 | E4: 25 | F4: =K4+SUMIFS(Purchases!$E$4:$E$50,Purchases!$C$4:$C$50,$A4)-SUMIFS('Sales Log'!$F$4:$F$120,'Sales Log'!$D$4:$D$120,$A4) -> 46 | G4: 15 | H4: =IF(F4<=G4,"REORDER","OK") -> OK | I4: =D4*F4 -> 828 | K4: 3
A5: P002 | B5: Royal Tru-Orange 300ml | C5: Drinks | D5: 18 | E5: 25 | F5: =K5+SUMIFS(Purchases!$E$4:$E$50,Purchases!$C$4:$C$50,$A5)-SUMIFS('Sales Log'!$F$4:$F$120,'Sales Log'!$D$4:$D$120,$A5) -> 30 | G5: 15 | H5: =IF(F5<=G5,"REORDER","OK") -> OK | I5: =D5*F5 -> 540 | K5: 0
A6: P003 | B6: Sprite 300ml | C6: Drinks | D6: 18 | E6: 25 | F6: =K6+SUMIFS(Purchases!$E$4:$E$50,Purchases!$C$4:$C$50,$A6)-SUMIFS('Sales Log'!$F$4:$F$120,'Sales Log'!$D$4:$D$120,$A6) -> 12 | G6: 15 | H6: =IF(F6<=G6,"REORDER","OK") -> REORDER | I6: =D6*F6 -> 216 | K6: 12
A7: P004 | B7: Lucky Me Pancit Canton | C7: Noodles | D7: 8.5 | E7: 12 | F7: =K7+SUMIFS(Purchases!$E$4:$E$50,Purchases!$C$4:$C$50,$A7)-SUMIFS('Sales Log'!$F$4:$F$120,'Sales Log'!$D$4:$D$120,$A7) -> 120 | G7: 30 | H7: =IF(F7<=G7,"REORDER","OK") -> OK | I7: =D7*F7 -> 1020 | K7: 20
A8: P005 | B8: Lucky Me Instant Mami | C8: Noodles | D8: 9 | E8: 13 | F8: =K8+SUMIFS(Purchases!$E$4:$E$50,Purchases!$C$4:$C$50,$A8)-SUMIFS('Sales Log'!$F$4:$F$120,'Sales Log'!$D$4:$D$120,$A8) -> 78 | G8: 30 | H8: =IF(F8<=G8,"REORDER","OK") -> OK | I8: =D8*F8 -> 702 | K8: 0
A9: P006 | B9: Nescafe 3in1 Coffee | C9: Coffee | D9: 7.5 | E9: 11 | F9: =K9+SUMIFS(Purchases!$E$4:$E$50,Purchases!$C$4:$C$50,$A9)-SUMIFS('Sales Log'!$F$4:$F$120,'Sales Log'!$D$4:$D$120,$A9) -> 10 | G9: 20 | H9: =IF(F9<=G9,"REORDER","OK") -> REORDER | I9: =D9*F9 -> 75 | K9: 10
A10: P007 | B10: Great Taste White Coffee | C10: Coffee | D10: 7 | E10: 10 | F10: =K10+SUMIFS(Purchases!$E$4:$E$50,Purchases!$C$4:$C$50,$A10)-SUMIFS('Sales Log'!$F$4:$F$120,'Sales Log'!$D$4:$D$120,$A10) -> 55 | G10: 20 | H10: =IF(F10<=G10,"REORDER","OK") -> OK | I10: =D10*F10 -> 385 | K10: 55
A11: P008 | B11: Bear Brand Powder 33g | C11: Milk | D11: 11 | E11: 15 | F11: =K11+SUMIFS(Purchases!$E$4:$E$50,Purchases!$C$4:$C$50,$A11)-SUMIFS('Sales Log'!$F$4:$F$120,'Sales Log'!$D$4:$D$120,$A11) -> 40 | G11: 15 | H11: =IF(F11<=G11,"REORDER","OK") -> OK | I11: =D11*F11 -> 440 | K11: 0
A12: P009 | B12: Alaska Powder 33g | C12: Milk | D12: 11 | E12: 15 | F12: =K12+SUMIFS(Purchases!$E$4:$E$50,Purchases!$C$4:$C$50,$A12)-SUMIFS('Sales Log'!$F$4:$F$120,'Sales Log'!$D$4:$D$120,$A12) -> 8 | G12: 15 | H12: =IF(F12<=G12,"REORDER","OK") -> REORDER | I12: =D12*F12 -> 88 | K12: 8
A13: P010 | B13: Argentinian Hotdog 250g | C13: Frozen | D13: 45 | E13: 60 | F13: =K13+SUMIFS(Purchases!$E$4:$E$50,Purchases!$C$4:$C$50,$A13)-SUMIFS('Sales Log'!$F$4:$F$120,'Sales Log'!$D$4:$D$120,$A13) -> 20 | G13: 8 | H13: =IF(F13<=G13,"REORDER","OK") -> OK | I13: =D13*F13 -> 900 | K13: 20
A14: P011 | B14: CDO Karne Norte 100g | C14: Canned | D14: 28 | E14: 38 | F14: =K14+SUMIFS(Purchases!$E$4:$E$50,Purchases!$C$4:$C$50,$A14)-SUMIFS('Sales Log'!$F$4:$F$120,'Sales Log'!$D$4:$D$120,$A14) -> 25 | G14: 10 | H14: =IF(F14<=G14,"REORDER","OK") -> OK | I14: =D14*F14 -> 700 | K14: 25
A15: P012 | B15: Lucky Me! Go Cup | C15: Noodles | D15: 18 | E15: 25 | F15: =K15+SUMIFS(Purchases!$E$4:$E$50,Purchases!$C$4:$C$50,$A15)-SUMIFS('Sales Log'!$F$4:$F$120,'Sales Log'!$D$4:$D$120,$A15) -> 30 | G15: 10 | H15: =IF(F15<=G15,"REORDER","OK") -> OK | I15: =D15*F15 -> 540 | K15: 30
... A21: P018 | B21: Silver Swan Soy Sauce 350ml | C21: Condiments | D21: 18 | E21: 25 | F21: =K21+SUMIFS(Purchases!$E$4:$E$50,Purchases!$C$4:$C$50,$A21)-SUMIFS('Sales Log'!$F$4:$F$120,'Sales Log'!$D$4:$D$120,$A21) -> 22 | G21: 8 | H21: =IF(F21<=G21,"REORDER","OK") -> OK | I21: =D21*F21 -> 396 | K21: 22
A24: TOTAL | F24: =SUM(F4:F21) -> 899 | I24: =SUM(I4:I21) -> 13849

Sheet Credit Ledger
A1: CUSTOMER CREDIT / UTANG LEDGER
A3: Date Borrowed | B3: Customer Name | C3: Item/s | D3: Amount Owed (₱) | E3: Date Paid | F3: Amount Paid (₱) | G3: Balance (₱) | H3: Status
A4: =IFERROR(INDEX('Sales Log'!$A:$A,MATCH(ROW()-3,'Sales Log'!$Z:$Z,0)),"") -> 46302 | B4: =IF(A4="","",IFERROR(INDEX('Sales Log'!$L:$L,MATCH(ROW()-3,'Sales Log'!$Z:$Z,0)),"")) -> Magtalas | C4: =IF(A4="","",IFERROR(INDEX('Sales Log'!$E:$E,MATCH(ROW()-3,'Sales Log'!$Z:$Z,0))&" x "&INDEX('Sales Log'!$F:$F,MATCH(ROW()-3,'Sales Log'!$Z:$Z,0))&" pcs","")) -> Lucky Me Instant Mami x 2 pcs | D4: =IF(A4="","",IFERROR(INDEX('Sales Log'!$H:$H,MATCH(ROW()-3,'Sales Log'!$Z:$Z,0)),"")) -> 26 | F4: 20 | G4: =IF(D4="","",D4-IF(F4="",0,F4)) -> 6 | H4: =IF(D4="","",IF(G4<=0,"PAID",IF(F4>0,"PARTIAL","UNPAID"))) -> PARTIAL
A5: =IFERROR(INDEX('Sales Log'!$A:$A,MATCH(ROW()-3,'Sales Log'!$Z:$Z,0)),"") | B5: =IF(A5="","",IFERROR(INDEX('Sales Log'!$L:$L,MATCH(ROW()-3,'Sales Log'!$Z:$Z,0)),"")) | C5: =IF(A5="","",IFERROR(INDEX('Sales Log'!$E:$E,MATCH(ROW()-3,'Sales Log'!$Z:$Z,0))&" x "&INDEX('Sales Log'!$F:$F,MATCH(ROW()-3,'Sales Log'!$Z:$Z,0))&" pcs","")) | D5: =IF(A5="","",IFERROR(INDEX('Sales Log'!$H:$H,MATCH(ROW()-3,'Sales Log'!$Z:$Z,0)),"")) | E5: =IF(N(F5)<=0,"",IF(N(E5)=0,TODAY(),E5)) | G5: =IF(D5="","",D5-IF(F5="",0,F5)) | H5: =IF(D5="","",IF(G5<=0,"PAID",IF(F5>0,"PARTIAL","UNPAID")))
A6: =IFERROR(INDEX('Sales Log'!$A:$A,MATCH(ROW()-3,'Sales Log'!$Z:$Z,0)),"") | B6: =IF(A6="","",IFERROR(INDEX('Sales Log'!$L:$L,MATCH(ROW()-3,'Sales Log'!$Z:$Z,0)),"")) | C6: =IF(A6="","",IFERROR(INDEX('Sales Log'!$E:$E,MATCH(ROW()-3,'Sales Log'!$Z:$Z,0))&" x "&INDEX('Sales Log'!$F:$F,MATCH(ROW()-3,'Sales Log'!$Z:$Z,0))&" pcs","")) | D6: =IF(A6="","",IFERROR(INDEX('Sales Log'!$H:$H,MATCH(ROW()-3,'Sales Log'!$Z:$Z,0)),"")) | E6: =IF(N(F6)<=0,"",IF(N(E6)=0,TODAY(),E6)) | G6: =IF(D6="","",D6-IF(F6="",0,F6)) | H6: =IF(D6="","",IF(G6<=0,"PAID",IF(F6>0,"PARTIAL","UNPAID")))
A7: =IFERROR(INDEX('Sales Log'!$A:$A,MATCH(ROW()-3,'Sales Log'!$Z:$Z,0)),"") | B7: =IF(A7="","",IFERROR(INDEX('Sales Log'!$L:$L,MATCH(ROW()-3,'Sales Log'!$Z:$Z,0)),"")) | C7: =IF(A7="","",IFERROR(INDEX('Sales Log'!$E:$E,MATCH(ROW()-3,'Sales Log'!$Z:$Z,0))&" x "&INDEX('Sales Log'!$F:$F,MATCH(ROW()-3,'Sales Log'!$Z:$Z,0))&" pcs","")) | D7: =IF(A7="","",IFERROR(INDEX('Sales Log'!$H:$H,MATCH(ROW()-3,'Sales Log'!$Z:$Z,0)),"")) | E7: =IF(N(F7)<=0,"",IF(N(E7)=0,TODAY(),E7)) | G7: =IF(D7="","",D7-IF(F7="",0,F7)) | H7: =IF(D7="","",IF(G7<=0,"PAID",IF(F7>0,"PARTIAL","UNPAID")))
A8: =IFERROR(INDEX('Sales Log'!$A:$A,MATCH(ROW()-3,'Sales Log'!$Z:$Z,0)),"") | B8: =IF(A8="","",IFERROR(INDEX('Sales Log'!$L:$L,MATCH(ROW()-3,'Sales Log'!$Z:$Z,0)),"")) | C8: =IF(A8="","",IFERROR(INDEX('Sales Log'!$E:$E,MATCH(ROW()-3,'Sales Log'!$Z:$Z,0))&" x "&INDEX('Sales Log'!$F:$F,MATCH(ROW()-3,'Sales Log'!$Z:$Z,0))&" pcs","")) | D8: =IF(A8="","",IFERROR(INDEX('Sales Log'!$H:$H,MATCH(ROW()-3,'Sales Log'!$Z:$Z,0)),"")) | E8: =IF(N(F8)<=0,"",IF(N(E8)=0,TODAY(),E8)) | G8: =IF(D8="","",D8-IF(F8="",0,F8)) | H8: =IF(D8="","",IF(G8<=0,"PAID",IF(F8>0,"PARTIAL","UNPAID")))
A9: =IFERROR(INDEX('Sales Log'!$A:$A,MATCH(ROW()-3,'Sales Log'!$Z:$Z,0)),"") | B9: =IF(A9="","",IFERROR(INDEX('Sales Log'!$L:$L,MATCH(ROW()-3,'Sales Log'!$Z:$Z,0)),"")) | C9: =IF(A9="","",IFERROR(INDEX('Sales Log'!$E:$E,MATCH(ROW()-3,'Sales Log'!$Z:$Z,0))&" x "&INDEX('Sales Log'!$F:$F,MATCH(ROW()-3,'Sales Log'!$Z:$Z,0))&" pcs","")) | D9: =IF(A9="","",IFERROR(INDEX('Sales Log'!$H:$H,MATCH(ROW()-3,'Sales Log'!$Z:$Z,0)),"")) | E9: =IF(N(F9)<=0,"",IF(N(E9)=0,TODAY(),E9)) | G9: =IF(D9="","",D9-IF(F9="",0,F9)) | H9: =IF(D9="","",IF(G9<=0,"PAID",IF(F9>0,"PARTIAL","UNPAID")))
A10: =IFERROR(INDEX('Sales Log'!$A:$A,MATCH(ROW()-3,'Sales Log'!$Z:$Z,0)),"") | B10: =IF(A10="","",IFERROR(INDEX('Sales Log'!$L:$L,MATCH(ROW()-3,'Sales Log'!$Z:$Z,0)),"")) | C10: =IF(A10="","",IFERROR(INDEX('Sales Log'!$E:$E,MATCH(ROW()-3,'Sales Log'!$Z:$Z,0))&" x "&INDEX('Sales Log'!$F:$F,MATCH(ROW()-3,'Sales Log'!$Z:$Z,0))&" pcs","")) | D10: =IF(A10="","",IFERROR(INDEX('Sales Log'!$H:$H,MATCH(ROW()-3,'Sales Log'!$Z:$Z,0)),"")) | E10: =IF(N(F10)<=0,"",IF(N(E10)=0,TODAY(),E10)) | G10: =IF(D10="","",D10-IF(F10="",0,F10)) | H10: =IF(D10="","",IF(G10<=0,"PAID",IF(F10>0,"PARTIAL","UNPAID")))
A11: =IFERROR(INDEX('Sales Log'!$A:$A,MATCH(ROW()-3,'Sales Log'!$Z:$Z,0)),"") | B11: =IF(A11="","",IFERROR(INDEX('Sales Log'!$L:$L,MATCH(ROW()-3,'Sales Log'!$Z:$Z,0)),"")) | C11: =IF(A11="","",IFERROR(INDEX('Sales Log'!$E:$E,MATCH(ROW()-3,'Sales Log'!$Z:$Z,0))&" x "&INDEX('Sales Log'!$F:$F,MATCH(ROW()-3,'Sales Log'!$Z:$Z,0))&" pcs","")) | D11: =IF(A11="","",IFERROR(INDEX('Sales Log'!$H:$H,MATCH(ROW()-3,'Sales Log'!$Z:$Z,0)),"")) | E11: =IF(N(F11)<=0,"",IF(N(E11)=0,TODAY(),E11)) | G11: =IF(D11="","",D11-IF(F11="",0,F11)) | H11: =IF(D11="","",IF(G11<=0,"PAID",IF(F11>0,"PARTIAL","UNPAID")))
A12: =IFERROR(INDEX('Sales Log'!$A:$A,MATCH(ROW()-3,'Sales Log'!$Z:$Z,0)),"") | B12: =IF(A12="","",IFERROR(INDEX('Sales Log'!$L:$L,MATCH(ROW()-3,'Sales Log'!$Z:$Z,0)),"")) | C12: =IF(A12="","",IFERROR(INDEX('Sales Log'!$E:$E,MATCH(ROW()-3,'Sales Log'!$Z:$Z,0))&" x "&INDEX('Sales Log'!$F:$F,MATCH(ROW()-3,'Sales Log'!$Z:$Z,0))&" pcs","")) | D12: =IF(A12="","",IFERROR(INDEX('Sales Log'!$H:$H,MATCH(ROW()-3,'Sales Log'!$Z:$Z,0)),"")) | E12: =IF(N(F12)<=0,"",IF(N(E12)=0,TODAY(),E12)) | G12: =IF(D12="","",D12-IF(F12="",0,F12)) | H12: =IF(D12="","",IF(G12<=0,"PAID",IF(F12>0,"PARTIAL","UNPAID")))
A13: =IFERROR(INDEX('Sales Log'!$A:$A,MATCH(ROW()-3,'Sales Log'!$Z:$Z,0)),"") | B13: =IF(A13="","",IFERROR(INDEX('Sales Log'!$L:$L,MATCH(ROW()-3,'Sales Log'!$Z:$Z,0)),"")) | C13: =IF(A13="","",IFERROR(INDEX('Sales Log'!$E:$E,MATCH(ROW()-3,'Sales Log'!$Z:$Z,0))&" x "&INDEX('Sales Log'!$F:$F,MATCH(ROW()-3,'Sales Log'!$Z:$Z,0))&" pcs","")) | D13: =IF(A13="","",IFERROR(INDEX('Sales Log'!$H:$H,MATCH(ROW()-3,'Sales Log'!$Z:$Z,0)),"")) | E13: =IF(N(F13)<=0,"",IF(N(E13)=0,TODAY(),E13)) | G13: =IF(D13="","",D13-IF(F13="",0,F13)) | H13: =IF(D13="","",IF(G13<=0,"PAID",IF(F13>0,"PARTIAL","UNPAID")))
A14: =IFERROR(INDEX('Sales Log'!$A:$A,MATCH(ROW()-3,'Sales Log'!$Z:$Z,0)),"") | B14: =IF(A14="","",IFERROR(INDEX('Sales Log'!$L:$L,MATCH(ROW()-3,'Sales Log'!$Z:$Z,0)),"")) | C14: =IF(A14="","",IFERROR(INDEX('Sales Log'!$E:$E,MATCH(ROW()-3,'Sales Log'!$Z:$Z,0))&" x "&INDEX('Sales Log'!$F:$F,MATCH(ROW()-3,'Sales Log'!$Z:$Z,0))&" pcs","")) | D14: =IF(A14="","",IFERROR(INDEX('Sales Log'!$H:$H,MATCH(ROW()-3,'Sales Log'!$Z:$Z,0)),"")) | E14: =IF(N(F14)<=0,"",IF(N(E14)=0,TODAY(),E14)) | G14: =IF(D14="","",D14-IF(F14="",0,F14)) | H14: =IF(D14="","",IF(G14<=0,"PAID",IF(F14>0,"PARTIAL","UNPAID")))
A15: =IFERROR(INDEX('Sales Log'!$A:$A,MATCH(ROW()-3,'Sales Log'!$Z:$Z,0)),"") | B15: =IF(A15="","",IFERROR(INDEX('Sales Log'!$L:$L,MATCH(ROW()-3,'Sales Log'!$Z:$Z,0)),"")) | C15: =IF(A15="","",IFERROR(INDEX('Sales Log'!$E:$E,MATCH(ROW()-3,'Sales Log'!$Z:$Z,0))&" x "&INDEX('Sales Log'!$F:$F,MATCH(ROW()-3,'Sales Log'!$Z:$Z,0))&" pcs","")) | D15: =IF(A15="","",IFERROR(INDEX('Sales Log'!$H:$H,MATCH(ROW()-3,'Sales Log'!$Z:$Z,0)),"")) | E15: =IF(N(F15)<=0,"",IF(N(E15)=0,TODAY(),E15)) | G15: =IF(D15="","",D15-IF(F15="",0,F15)) | H15: =IF(D15="","",IF(G15<=0,"PAID",IF(F15>0,"PARTIAL","UNPAID")))
A16: =IFERROR(INDEX('Sales Log'!$A:$A,MATCH(ROW()-3,'Sales Log'!$Z:$Z,0)),"") | B16: =IF(A16="","",IFERROR(INDEX('Sales Log'!$L:$L,MATCH(ROW()-3,'Sales Log'!$Z:$Z,0)),"")) | C16: =IF(A16="","",IFERROR(INDEX('Sales Log'!$E:$E,MATCH(ROW()-3,'Sales Log'!$Z:$Z,0))&" x "&INDEX('Sales Log'!$F:$F,MATCH(ROW()-3,'Sales Log'!$Z:$Z,0))&" pcs","")) | D16: =IF(A16="","",IFERROR(INDEX('Sales Log'!$H:$H,MATCH(ROW()-3,'Sales Log'!$Z:$Z,0)),"")) | E16: =IF(N(F16)<=0,"",IF(N(E16)=0,TODAY(),E16)) | G16: =IF(D16="","",D16-IF(F16="",0,F16)) | H16: =IF(D16="","",IF(G16<=0,"PAID",IF(F16>0,"PARTIAL","UNPAID")))
... A60: =IFERROR(INDEX('Sales Log'!$A:$A,MATCH(ROW()-3,'Sales Log'!$Z:$Z,0)),"") | B60: =IF(A60="","",IFERROR(INDEX('Sales Log'!$L:$L,MATCH(ROW()-3,'Sales Log'!$Z:$Z,0)),"")) | C60: =IF(A60="","",IFERROR(INDEX('Sales Log'!$E:$E,MATCH(ROW()-3,'Sales Log'!$Z:$Z,0))&" x "&INDEX('Sales Log'!$F:$F,MATCH(ROW()-3,'Sales Log'!$Z:$Z,0))&" pcs","")) | D60: =IF(A60="","",IFERROR(INDEX('Sales Log'!$H:$H,MATCH(ROW()-3,'Sales Log'!$Z:$Z,0)),"")) | E60: =IF(N(F60)<=0,"",IF(N(E60)=0,TODAY(),E60)) | G60: =IF(D60="","",D60-IF(F60="",0,F60)) | H60: =IF(D60="","",IF(G60<=0,"PAID",IF(F60>0,"PARTIAL","UNPAID")))
A61: TOTAL OUTSTANDING | G61: =SUMIF(G4:G60,">0") -> 6

Sheet Purchases
A1: SUPPLIER PURCHASES / RESTOCK RECORD
A3: Date | B3: Supplier | C3: Product ID | D3: Product Name | E3: Qty Bought | F3: Unit Cost (₱) | G3: Total Cost (₱)
A4: 46295 | B4: Coca-Cola Distributor | C4: P001 | D4: =IF(C4="","",VLOOKUP(C4,Inventory!$A$4:$B$21,2,FALSE())) -> Coke Mismo 300ml | E4: 48 | F4: 18 | G4: =IF(OR(E4="",F4=""),"",E4*F4) -> 864
A5: 46295 | B5: Coca-Cola Distributor | C5: P002 | D5: =IF(C5="","",VLOOKUP(C5,Inventory!$A$4:$B$21,2,FALSE())) -> Royal Tru-Orange 300ml | E5: 36 | F5: 18 | G5: =IF(OR(E5="",F5=""),"",E5*F5) -> 648
A6: 46295 | B6: Monde Nissin Dealer | C6: P004 | D6: =IF(C6="","",VLOOKUP(C6,Inventory!$A$4:$B$21,2,FALSE())) -> Lucky Me Pancit Canton | E6: 100 | F6: 8.5 | G6: =IF(OR(E6="",F6=""),"",E6*F6) -> 850
A7: 46295 | B7: Monde Nissin Dealer | C7: P005 | D7: =IF(C7="","",VLOOKUP(C7,Inventory!$A$4:$B$21,2,FALSE())) -> Lucky Me Instant Mami | E7: 80 | F7: 9 | G7: =IF(OR(E7="",F7=""),"",E7*F7) -> 720
A8: 46295 | B8: Nestle Distributor | C8: P008 | D8: =IF(C8="","",VLOOKUP(C8,Inventory!$A$4:$B$21,2,FALSE())) -> Bear Brand Powder 33g | E8: 40 | F8: 11 | G8: =IF(OR(E8="",F8=""),"",E8*F8) -> 440
A9: 46295 | B9: Rice Wholesaler | C9: P015 | D9: =IF(C9="","",VLOOKUP(C9,Inventory!$A$4:$B$21,2,FALSE())) -> Rice (per kg) | E9: 100 | F9: 42 | G9: =IF(OR(E9="",F9=""),"",E9*F9) -> 4200
A10: =IF(OR(C10="",E10=""),"",IF(N(A10)=0,TODAY(),A10)) | D10: =IF(C10="","",VLOOKUP(C10,Inventory!$A$4:$B$21,2,FALSE())) | F10: =IF(C10="","",VLOOKUP(C10,Inventory!$A$4:$D$21,4,FALSE())) | G10: =IF(OR(E10="",F10=""),"",E10*F10)
A11: =IF(OR(C11="",E11=""),"",IF(N(A11)=0,TODAY(),A11)) | D11: =IF(C11="","",VLOOKUP(C11,Inventory!$A$4:$B$21,2,FALSE())) | F11: =IF(C11="","",VLOOKUP(C11,Inventory!$A$4:$D$21,4,FALSE())) | G11: =IF(OR(E11="",F11=""),"",E11*F11)
A12: =IF(OR(C12="",E12=""),"",IF(N(A12)=0,TODAY(),A12)) | D12: =IF(C12="","",VLOOKUP(C12,Inventory!$A$4:$B$21,2,FALSE())) | F12: =IF(C12="","",VLOOKUP(C12,Inventory!$A$4:$D$21,4,FALSE())) | G12: =IF(OR(E12="",F12=""),"",E12*F12)
A13: =IF(OR(C13="",E13=""),"",IF(N(A13)=0,TODAY(),A13)) | D13: =IF(C13="","",VLOOKUP(C13,Inventory!$A$4:$B$21,2,FALSE())) | F13: =IF(C13="","",VLOOKUP(C13,Inventory!$A$4:$D$21,4,FALSE())) | G13: =IF(OR(E13="",F13=""),"",E13*F13)
A14: =IF(OR(C14="",E14=""),"",IF(N(A14)=0,TODAY(),A14)) | D14: =IF(C14="","",VLOOKUP(C14,Inventory!$A$4:$B$21,2,FALSE())) | F14: =IF(C14="","",VLOOKUP(C14,Inventory!$A$4:$D$21,4,FALSE())) | G14: =IF(OR(E14="",F14=""),"",E14*F14)
A15: =IF(OR(C15="",E15=""),"",IF(N(A15)=0,TODAY(),A15)) | D15: =IF(C15="","",VLOOKUP(C15,Inventory!$A$4:$B$21,2,FALSE())) | F15: =IF(C15="","",VLOOKUP(C15,Inventory!$A$4:$D$21,4,FALSE())) | G15: =IF(OR(E15="",F15=""),"",E15*F15)
A16: =IF(OR(C16="",E16=""),"",IF(N(A16)=0,TODAY(),A16)) | D16: =IF(C16="","",VLOOKUP(C16,Inventory!$A$4:$B$21,2,FALSE())) | F16: =IF(C16="","",VLOOKUP(C16,Inventory!$A$4:$D$21,4,FALSE())) | G16: =IF(OR(E16="",F16=""),"",E16*F16)
A17: =IF(OR(C17="",E17=""),"",IF(N(A17)=0,TODAY(),A17)) | D17: =IF(C17="","",VLOOKUP(C17,Inventory!$A$4:$B$21,2,FALSE())) | F17: =IF(C17="","",VLOOKUP(C17,Inventory!$A$4:$D$21,4,FALSE())) | G17: =IF(OR(E17="",F17=""),"",E17*F17)
A18: =IF(OR(C18="",E18=""),"",IF(N(A18)=0,TODAY(),A18)) | D18: =IF(C18="","",VLOOKUP(C18,Inventory!$A$4:$B$21,2,FALSE())) | F18: =IF(C18="","",VLOOKUP(C18,Inventory!$A$4:$D$21,4,FALSE())) | G18: =IF(OR(E18="",F18=""),"",E18*F18)
A19: =IF(OR(C19="",E19=""),"",IF(N(A19)=0,TODAY(),A19)) | D19: =IF(C19="","",VLOOKUP(C19,Inventory!$A$4:$B$21,2,FALSE())) | F19: =IF(C19="","",VLOOKUP(C19,Inventory!$A$4:$D$21,4,FALSE())) | G19: =IF(OR(E19="",F19=""),"",E19*F19)
A20: =IF(OR(C20="",E20=""),"",IF(N(A20)=0,TODAY(),A20)) | D20: =IF(C20="","",VLOOKUP(C20,Inventory!$A$4:$B$21,2,FALSE())) | F20: =IF(C20="","",VLOOKUP(C20,Inventory!$A$4:$D$21,4,FALSE())) | G20: =IF(OR(E20="",F20=""),"",E20*F20)
A21: =IF(OR(C21="",E21=""),"",IF(N(A21)=0,TODAY(),A21)) | D21: =IF(C21="","",VLOOKUP(C21,Inventory!$A$4:$B$21,2,FALSE())) | F21: =IF(C21="","",VLOOKUP(C21,Inventory!$A$4:$D$21,4,FALSE())) | G21: =IF(OR(E21="",F21=""),"",E21*F21)
... A50: =IF(OR(C50="",E50=""),"",IF(N(A50)=0,TODAY(),A50)) | D50: =IF(C50="","",VLOOKUP(C50,Inventory!$A$4:$B$21,2,FALSE())) | F50: =IF(C50="","",VLOOKUP(C50,Inventory!$A$4:$D$21,4,FALSE())) | G50: =IF(OR(E50="",F50=""),"",E50*F50)
A51: TOTAL PURCHASES | G51: =SUM(G4:G50) -> 7722

Sheet Reports
A1: AUTO GENERATED SALES & PROFIT REPORTS
A3: DAILY SALES (LAST 7 DAYS)
A4: Date | B4: Total Sales (₱) | C4: Total Cost (₱) | D4: Gross Profit (₱) | E4: Items Sold | F4: Margin %
A5: =TODAY()-6 -> 46296 | B5: =SUMIFS('Sales Log'!$H$4:$H$120,'Sales Log'!$A$4:$A$120,A5) -> 0 | C5: =SUMIFS('Sales Log'!$I$4:$I$120,'Sales Log'!$A$4:$A$120,A5) -> 0 | D5: =B5-C5 -> 0 | E5: =SUMIFS('Sales Log'!$F$4:$F$120,'Sales Log'!$A$4:$A$120,A5) -> 0 | F5: =IF(B5=0,"",D5/B5)
A6: =A5+1 -> 46297 | B6: =SUMIFS('Sales Log'!$H$4:$H$120,'Sales Log'!$A$4:$A$120,A6) -> 0 | C6: =SUMIFS('Sales Log'!$I$4:$I$120,'Sales Log'!$A$4:$A$120,A6) -> 0 | D6: =B6-C6 -> 0 | E6: =SUMIFS('Sales Log'!$F$4:$F$120,'Sales Log'!$A$4:$A$120,A6) -> 0 | F6: =IF(B6=0,"",D6/B6)
A7: =A6+1 -> 46298 | B7: =SUMIFS('Sales Log'!$H$4:$H$120,'Sales Log'!$A$4:$A$120,A7) -> 0 | C7: =SUMIFS('Sales Log'!$I$4:$I$120,'Sales Log'!$A$4:$A$120,A7) -> 0 | D7: =B7-C7 -> 0 | E7: =SUMIFS('Sales Log'!$F$4:$F$120,'Sales Log'!$A$4:$A$120,A7) -> 0 | F7: =IF(B7=0,"",D7/B7)
A8: =A7+1 -> 46299 | B8: =SUMIFS('Sales Log'!$H$4:$H$120,'Sales Log'!$A$4:$A$120,A8) -> 0 | C8: =SUMIFS('Sales Log'!$I$4:$I$120,'Sales Log'!$A$4:$A$120,A8) -> 0 | D8: =B8-C8 -> 0 | E8: =SUMIFS('Sales Log'!$F$4:$F$120,'Sales Log'!$A$4:$A$120,A8) -> 0 | F8: =IF(B8=0,"",D8/B8)
A9: =A8+1 -> 46300 | B9: =SUMIFS('Sales Log'!$H$4:$H$120,'Sales Log'!$A$4:$A$120,A9) -> 0 | C9: =SUMIFS('Sales Log'!$I$4:$I$120,'Sales Log'!$A$4:$A$120,A9) -> 0 | D9: =B9-C9 -> 0 | E9: =SUMIFS('Sales Log'!$F$4:$F$120,'Sales Log'!$A$4:$A$120,A9) -> 0 | F9: =IF(B9=0,"",D9/B9)
A10: =A9+1 -> 46301 | B10: =SUMIFS('Sales Log'!$H$4:$H$120,'Sales Log'!$A$4:$A$120,A10) -> 0 | C10: =SUMIFS('Sales Log'!$I$4:$I$120,'Sales Log'!$A$4:$A$120,A10) -> 0 | D10: =B10-C10 -> 0 | E10: =SUMIFS('Sales Log'!$F$4:$F$120,'Sales Log'!$A$4:$A$120,A10) -> 0 | F10: =IF(B10=0,"",D10/B10)
A11: =A10+1 -> 46302 | B11: =SUMIFS('Sales Log'!$H$4:$H$120,'Sales Log'!$A$4:$A$120,A11) -> 301 | C11: =SUMIFS('Sales Log'!$I$4:$I$120,'Sales Log'!$A$4:$A$120,A11) -> 216 | D11: =B11-C11 -> 85 | E11: =SUMIFS('Sales Log'!$F$4:$F$120,'Sales Log'!$A$4:$A$120,A11) -> 13 | F11: =IF(B11=0,"",D11/B11) -> 0.28239203
A13: PERIOD SUMMARY
A14: Period | B14: Total Sales (₱) | C14: Total Cost (₱) | D14: Gross Profit (₱) | E14: Items Sold | F14: Margin %
A15: Today | B15: =SUMIFS('Sales Log'!$H$4:$H$120,'Sales Log'!$A$4:$A$120,TODAY()) -> 301 | C15: =SUMIFS('Sales Log'!$I$4:$I$120,'Sales Log'!$A$4:$A$120,TODAY()) -> 216 | D15: =B15-C15 -> 85 | E15: =SUMIFS('Sales Log'!$F$4:$F$120,'Sales Log'!$A$4:$A$120,TODAY()) -> 13 | F15: =IF(B15=0,"",D15/B15) -> 0.28239203
A16: This Week (Mon-Sun) | B16: =SUMIFS('Sales Log'!$H$4:$H$120,'Sales Log'!$A$4:$A$120,">="&TODAY()-WEEKDAY(TODAY(),2)+1,'Sales Log'!$A$4:$A$120,"<"&TODAY()-WEEKDAY(TODAY(),2)+8) -> 301 | C16: =SUMIFS('Sales Log'!$I$4:$I$120,'Sales Log'!$A$4:$A$120,">="&TODAY()-WEEKDAY(TODAY(),2)+1,'Sales Log'!$A$4:$A$120,"<"&TODAY()-WEEKDAY(TODAY(),2)+8) -> 216 | D16: =B16-C16 -> 85 | E16: =SUMIFS('Sales Log'!$F$4:$F$120,'Sales Log'!$A$4:$A$120,">="&TODAY()-WEEKDAY(TODAY(),2)+1,'Sales Log'!$A$4:$A$120,"<"&TODAY()-WEEKDAY(TODAY(),2)+8) -> 13 | F16: =IF(B16=0,"",D16/B16) -> 0.28239203
A17: This Month | B17: =SUMIFS('Sales Log'!$H$4:$H$120,'Sales Log'!$A$4:$A$120,">="&DATE(YEAR(TODAY()),MONTH(TODAY()),1),'Sales Log'!$A$4:$A$120,"<="&EOMONTH(TODAY(),0)) -> 301 | C17: =SUMIFS('Sales Log'!$I$4:$I$120,'Sales Log'!$A$4:$A$120,">="&DATE(YEAR(TODAY()),MONTH(TODAY()),1),'Sales Log'!$A$4:$A$120,"<="&EOMONTH(TODAY(),0)) -> 216 | D17: =B17-C17 -> 85 | E17: =SUMIFS('Sales Log'!$F$4:$F$120,'Sales Log'!$A$4:$A$120,">="&DATE(YEAR(TODAY()),MONTH(TODAY()),1),'Sales Log'!$A$4:$A$120,"<="&EOMONTH(TODAY(),0)) -> 13 | F17: =IF(B17=0,"",D17/B17) -> 0.28239203
A19: TOP SELLING PRODUCTS (BY QUANTITY)
A20: Rank | B20: Product Name | C20: Qty Sold | D20: Total Sales (₱) | E20: Total Profit (₱)
A21: 1 | B21: =INDEX(Inventory!$B$4:$B$21,K21) -> Royal Tru-Orange 300ml | C21: =INDEX($I$21:$I$38,K21) -> 6 | D21: =SUMIFS('Sales Log'!$H$4:$H$120,'Sales Log'!$D$4:$D$120,INDEX($H$21:$H$38,K21)) -> 150 | E21: =SUMIFS('Sales Log'!$J$4:$J$120,'Sales Log'!$D$4:$D$120,INDEX($H$21:$H$38,K21)) -> 42 | H21: =Inventory!$A$4 -> P001 | I21: =SUMIFS('Sales Log'!$F$4:$F$120,'Sales Log'!$D$4:$D$120,H21) -> 5 | J21: =I21*1000+(1000-ROWS($H$21:H21)) -> 5999 | K21: =MATCH(LARGE($J$21:$J$38,A21),$J$21:$J$38,0) -> 2
A22: 2 | B22: =INDEX(Inventory!$B$4:$B$21,K22) -> Coke Mismo 300ml | C22: =INDEX($I$21:$I$38,K22) -> 5 | D22: =SUMIFS('Sales Log'!$H$4:$H$120,'Sales Log'!$D$4:$D$120,INDEX($H$21:$H$38,K22)) -> 125 | E22: =SUMIFS('Sales Log'!$J$4:$J$120,'Sales Log'!$D$4:$D$120,INDEX($H$21:$H$38,K22)) -> 35 | H22: =Inventory!$A$5 -> P002 | I22: =SUMIFS('Sales Log'!$F$4:$F$120,'Sales Log'!$D$4:$D$120,H22) -> 6 | J22: =I22*1000+(1000-ROWS($H$21:H22)) -> 6998 | K22: =MATCH(LARGE($J$21:$J$38,A22),$J$21:$J$38,0) -> 1
A23: 3 | B23: =INDEX(Inventory!$B$4:$B$21,K23) -> Lucky Me Instant Mami | C23: =INDEX($I$21:$I$38,K23) -> 2 | D23: =SUMIFS('Sales Log'!$H$4:$H$120,'Sales Log'!$D$4:$D$120,INDEX($H$21:$H$38,K23)) -> 26 | E23: =SUMIFS('Sales Log'!$J$4:$J$120,'Sales Log'!$D$4:$D$120,INDEX($H$21:$H$38,K23)) -> 8 | H23: =Inventory!$A$6 -> P003 | I23: =SUMIFS('Sales Log'!$F$4:$F$120,'Sales Log'!$D$4:$D$120,H23) -> 0 | J23: =I23*1000+(1000-ROWS($H$21:H23)) -> 997 | K23: =MATCH(LARGE($J$21:$J$38,A23),$J$21:$J$38,0) -> 5
A24: 4 | B24: =INDEX(Inventory!$B$4:$B$21,K24) -> Sprite 300ml | C24: =INDEX($I$21:$I$38,K24) -> 0 | D24: =SUMIFS('Sales Log'!$H$4:$H$120,'Sales Log'!$D$4:$D$120,INDEX($H$21:$H$38,K24)) -> 0 | E24: =SUMIFS('Sales Log'!$J$4:$J$120,'Sales Log'!$D$4:$D$120,INDEX($H$21:$H$38,K24)) -> 0 | H24: =Inventory!$A$7 -> P004 | I24: =SUMIFS('Sales Log'!$F$4:$F$120,'Sales Log'!$D$4:$D$120,H24) -> 0 | J24: =I24*1000+(1000-ROWS($H$21:H24)) -> 996 | K24: =MATCH(LARGE($J$21:$J$38,A24),$J$21:$J$38,0) -> 3
A25: 5 | B25: =INDEX(Inventory!$B$4:$B$21,K25) -> Lucky Me Pancit Canton | C25: =INDEX($I$21:$I$38,K25) -> 0 | D25: =SUMIFS('Sales Log'!$H$4:$H$120,'Sales Log'!$D$4:$D$120,INDEX($H$21:$H$38,K25)) -> 0 | E25: =SUMIFS('Sales Log'!$J$4:$J$120,'Sales Log'!$D$4:$D$120,INDEX($H$21:$H$38,K25)) -> 0 | H25: =Inventory!$A$8 -> P005 | I25: =SUMIFS('Sales Log'!$F$4:$F$120,'Sales Log'!$D$4:$D$120,H25) -> 2 | J25: =I25*1000+(1000-ROWS($H$21:H25)) -> 2995 | K25: =MATCH(LARGE($J$21:$J$38,A25),$J$21:$J$38,0) -> 4
A26: 6 | B26: =INDEX(Inventory!$B$4:$B$21,K26) -> Nescafe 3in1 Coffee | C26: =INDEX($I$21:$I$38,K26) -> 0 | D26: =SUMIFS('Sales Log'!$H$4:$H$120,'Sales Log'!$D$4:$D$120,INDEX($H$21:$H$38,K26)) -> 0 | E26: =SUMIFS('Sales Log'!$J$4:$J$120,'Sales Log'!$D$4:$D$120,INDEX($H$21:$H$38,K26)) -> 0 | H26: =Inventory!$A$9 -> P006 | I26: =SUMIFS('Sales Log'!$F$4:$F$120,'Sales Log'!$D$4:$D$120,H26) -> 0 | J26: =I26*1000+(1000-ROWS($H$21:H26)) -> 994 | K26: =MATCH(LARGE($J$21:$J$38,A26),$J$21:$J$38,0) -> 6
A27: 7 | B27: =INDEX(Inventory!$B$4:$B$21,K27) -> Great Taste White Coffee | C27: =INDEX($I$21:$I$38,K27) -> 0 | D27: =SUMIFS('Sales Log'!$H$4:$H$120,'Sales Log'!$D$4:$D$120,INDEX($H$21:$H$38,K27)) -> 0 | E27: =SUMIFS('Sales Log'!$J$4:$J$120,'Sales Log'!$D$4:$D$120,INDEX($H$21:$H$38,K27)) -> 0 | H27: =Inventory!$A$10 -> P007 | I27: =SUMIFS('Sales Log'!$F$4:$F$120,'Sales Log'!$D$4:$D$120,H27) -> 0 | J27: =I27*1000+(1000-ROWS($H$21:H27)) -> 993 | K27: =MATCH(LARGE($J$21:$J$38,A27),$J$21:$J$38,0) -> 7
A28: 8 | B28: =INDEX(Inventory!$B$4:$B$21,K28) -> Bear Brand Powder 33g | C28: =INDEX($I$21:$I$38,K28) -> 0 | D28: =SUMIFS('Sales Log'!$H$4:$H$120,'Sales Log'!$D$4:$D$120,INDEX($H$21:$H$38,K28)) -> 0 | E28: =SUMIFS('Sales Log'!$J$4:$J$120,'Sales Log'!$D$4:$D$120,INDEX($H$21:$H$38,K28)) -> 0 | H28: =Inventory!$A$11 -> P008 | I28: =SUMIFS('Sales Log'!$F$4:$F$120,'Sales Log'!$D$4:$D$120,H28) -> 0 | J28: =I28*1000+(1000-ROWS($H$21:H28)) -> 992 | K28: =MATCH(LARGE($J$21:$J$38,A28),$J$21:$J$38,0) -> 8
A29: 9 | B29: =INDEX(Inventory!$B$4:$B$21,K29) -> Alaska Powder 33g | C29: =INDEX($I$21:$I$38,K29) -> 0 | D29: =SUMIFS('Sales Log'!$H$4:$H$120,'Sales Log'!$D$4:$D$120,INDEX($H$21:$H$38,K29)) -> 0 | E29: =SUMIFS('Sales Log'!$J$4:$J$120,'Sales Log'!$D$4:$D$120,INDEX($H$21:$H$38,K29)) -> 0 | H29: =Inventory!$A$12 -> P009 | I29: =SUMIFS('Sales Log'!$F$4:$F$120,'Sales Log'!$D$4:$D$120,H29) -> 0 | J29: =I29*1000+(1000-ROWS($H$21:H29)) -> 991 | K29: =MATCH(LARGE($J$21:$J$38,A29),$J$21:$J$38,0) -> 9
A30: 10 | B30: =INDEX(Inventory!$B$4:$B$21,K30) -> Argentinian Hotdog 250g | C30: =INDEX($I$21:$I$38,K30) -> 0 | D30: =SUMIFS('Sales Log'!$H$4:$H$120,'Sales Log'!$D$4:$D$120,INDEX($H$21:$H$38,K30)) -> 0 | E30: =SUMIFS('Sales Log'!$J$4:$J$120,'Sales Log'!$D$4:$D$120,INDEX($H$21:$H$38,K30)) -> 0 | H30: =Inventory!$A$13 -> P010 | I30: =SUMIFS('Sales Log'!$F$4:$F$120,'Sales Log'!$D$4:$D$120,H30) -> 0 | J30: =I30*1000+(1000-ROWS($H$21:H30)) -> 990 | K30: =MATCH(LARGE($J$21:$J$38,A30),$J$21:$J$38,0) -> 10
A31: 11 | B31: =INDEX(Inventory!$B$4:$B$21,K31) -> CDO Karne Norte 100g | C31: =INDEX($I$21:$I$38,K31) -> 0 | D31: =SUMIFS('Sales Log'!$H$4:$H$120,'Sales Log'!$D$4:$D$120,INDEX($H$21:$H$38,K31)) -> 0 | E31: =SUMIFS('Sales Log'!$J$4:$J$120,'Sales Log'!$D$4:$D$120,INDEX($H$21:$H$38,K31)) -> 0 | H31: =Inventory!$A$14 -> P011 | I31: =SUMIFS('Sales Log'!$F$4:$F$120,'Sales Log'!$D$4:$D$120,H31) -> 0 | J31: =I31*1000+(1000-ROWS($H$21:H31)) -> 989 | K31: =MATCH(LARGE($J$21:$J$38,A31),$J$21:$J$38,0) -> 11
A32: 12 | B32: =INDEX(Inventory!$B$4:$B$21,K32) -> Lucky Me! Go Cup | C32: =INDEX($I$21:$I$38,K32) -> 0 | D32: =SUMIFS('Sales Log'!$H$4:$H$120,'Sales Log'!$D$4:$D$120,INDEX($H$21:$H$38,K32)) -> 0 | E32: =SUMIFS('Sales Log'!$J$4:$J$120,'Sales Log'!$D$4:$D$120,INDEX($H$21:$H$38,K32)) -> 0 | H32: =Inventory!$A$15 -> P012 | I32: =SUMIFS('Sales Log'!$F$4:$F$120,'Sales Log'!$D$4:$D$120,H32) -> 0 | J32: =I32*1000+(1000-ROWS($H$21:H32)) -> 988 | K32: =MATCH(LARGE($J$21:$J$38,A32),$J$21:$J$38,0) -> 12
A33: 13 | B33: =INDEX(Inventory!$B$4:$B$21,K33) -> Piatos Chips | C33: =INDEX($I$21:$I$38,K33) -> 0 | D33: =SUMIFS('Sales Log'!$H$4:$H$120,'Sales Log'!$D$4:$D$120,INDEX($H$21:$H$38,K33)) -> 0 | E33: =SUMIFS('Sales Log'!$J$4:$J$120,'Sales Log'!$D$4:$D$120,INDEX($H$21:$H$38,K33)) -> 0 | H33: =Inventory!$A$16 -> P013 | I33: =SUMIFS('Sales Log'!$F$4:$F$120,'Sales Log'!$D$4:$D$120,H33) -> 0 | J33: =I33*1000+(1000-ROWS($H$21:H33)) -> 987 | K33: =MATCH(LARGE($J$21:$J$38,A33),$J$21:$J$38,0) -> 13
A34: 14 | B34: =INDEX(Inventory!$B$4:$B$21,K34) -> Chicharap | C34: =INDEX($I$21:$I$38,K34) -> 0 | D34: =SUMIFS('Sales Log'!$H$4:$H$120,'Sales Log'!$D$4:$D$120,INDEX($H$21:$H$38,K34)) -> 0 | E34: =SUMIFS('Sales Log'!$J$4:$J$120,'Sales Log'!$D$4:$D$120,INDEX($H$21:$H$38,K34)) -> 0 | H34: =Inventory!$A$17 -> P014 | I34: =SUMIFS('Sales Log'!$F$4:$F$120,'Sales Log'!$D$4:$D$120,H34) -> 0 | J34: =I34*1000+(1000-ROWS($H$21:H34)) -> 986 | K34: =MATCH(LARGE($J$21:$J$38,A34),$J$21:$J$38,0) -> 14
A35: 15 | B35: =INDEX(Inventory!$B$4:$B$21,K35) -> Rice (per kg) | C35: =INDEX($I$21:$I$38,K35) -> 0 | D35: =SUMIFS('Sales Log'!$H$4:$H$120,'Sales Log'!$D$4:$D$120,INDEX($H$21:$H$38,K35)) -> 0 | E35: =SUMIFS('Sales Log'!$J$4:$J$120,'Sales Log'!$D$4:$D$120,INDEX($H$21:$H$38,K35)) -> 0 | H35: =Inventory!$A$18 -> P015 | I35: =SUMIFS('Sales Log'!$F$4:$F$120,'Sales Log'!$D$4:$D$120,H35) -> 0 | J35: =I35*1000+(1000-ROWS($H$21:H35)) -> 985 | K35: =MATCH(LARGE($J$21:$J$38,A35),$J$21:$J$38,0) -> 15
A36: 16 | B36: =INDEX(Inventory!$B$4:$B$21,K36) -> Egg (per piece) | C36: =INDEX($I$21:$I$38,K36) -> 0 | D36: =SUMIFS('Sales Log'!$H$4:$H$120,'Sales Log'!$D$4:$D$120,INDEX($H$21:$H$38,K36)) -> 0 | E36: =SUMIFS('Sales Log'!$J$4:$J$120,'Sales Log'!$D$4:$D$120,INDEX($H$21:$H$38,K36)) -> 0 | H36: =Inventory!$A$19 -> P016 | I36: =SUMIFS('Sales Log'!$F$4:$F$120,'Sales Log'!$D$4:$D$120,H36) -> 0 | J36: =I36*1000+(1000-ROWS($H$21:H36)) -> 984 | K36: =MATCH(LARGE($J$21:$J$38,A36),$J$21:$J$38,0) -> 16
A37: 17 | B37: =INDEX(Inventory!$B$4:$B$21,K37) -> Datu Puti Vinegar 350ml | C37: =INDEX($I$21:$I$38,K37) -> 0 | D37: =SUMIFS('Sales Log'!$H$4:$H$120,'Sales Log'!$D$4:$D$120,INDEX($H$21:$H$38,K37)) -> 0 | E37: =SUMIFS('Sales Log'!$J$4:$J$120,'Sales Log'!$D$4:$D$120,INDEX($H$21:$H$38,K37)) -> 0 | H37: =Inventory!$A$20 -> P017 | I37: =SUMIFS('Sales Log'!$F$4:$F$120,'Sales Log'!$D$4:$D$120,H37) -> 0 | J37: =I37*1000+(1000-ROWS($H$21:H37)) -> 983 | K37: =MATCH(LARGE($J$21:$J$38,A37),$J$21:$J$38,0) -> 17
A38: 18 | B38: =INDEX(Inventory!$B$4:$B$21,K38) -> Silver Swan Soy Sauce 350ml | C38: =INDEX($I$21:$I$38,K38) -> 0 | D38: =SUMIFS('Sales Log'!$H$4:$H$120,'Sales Log'!$D$4:$D$120,INDEX($H$21:$H$38,K38)) -> 0 | E38: =SUMIFS('Sales Log'!$J$4:$J$120,'Sales Log'!$D$4:$D$120,INDEX($H$21:$H$38,K38)) -> 0 | H38: =Inventory!$A$21 -> P018 | I38: =SUMIFS('Sales Log'!$F$4:$F$120,'Sales Log'!$D$4:$D$120,H38) -> 0 | J38: =I38*1000+(1000-ROWS($H$21:H38)) -> 982 | K38: =MATCH(LARGE($J$21:$J$38,A38),$J$21:$J$38,0) -> 18
